mwin/__init__.py
mwin/_client.py
mwin/_exception.py
mwin/cli.py
mwin/logger.py
mwin/client/__init__.py
mwin/client/config.py
mwin/client/sync_client.py
mwin/client/schemas/__init__.py
mwin/client/schemas/request/__init__.py
mwin/client/schemas/request/log_request.py
mwin/client/schemas/response/__init__.py
mwin/client/schemas/response/log_response.py
mwin/config/__init__.py
mwin/config/configurator.py
mwin/config/loader.py
mwin/config/types.py
mwin/context/__init__.py
mwin/context/func_context.py
mwin/context/storage.py
mwin/helper/__init__.py
mwin/helper/args_helper.py
mwin/helper/cli_helper.py
mwin/helper/exception_helper.py
mwin/helper/id_helper.py
mwin/helper/inspect_helper.py
mwin/helper/serialize_helper.py
mwin/helper/llm/__init__.py
mwin/helper/llm/openai_helper.py
mwin/models/__init__.py
mwin/models/common.py
mwin/models/key_models.py
mwin/patches/std.py
mwin/patches/openai/async_completions.py
mwin/patches/openai/completions.py
mwin/track/__init__.py
mwin/track/_types.py
mwin/track/at_track.py
mwin/track/base.py
mwin/track/options.py
mwin-0.1.6.dist-info/licenses/LICENSE
mwin-0.1.6.dist-info/METADATA
mwin-0.1.6.dist-info/WHEEL
mwin-0.1.6.dist-info/entry_points.txt
mwin-0.1.6.dist-info/top_level.txt
mwin-0.1.6.dist-info/RECORD
