Metadata-Version: 2.4
Name: mwin
Version: 0.1.6
Summary: Track OpenAI, Claude, Gemini and OpenAI-compatible models then give solutions to improve your agent system.
Author-email: yanghui <dasss90ovo@gmail.com>
Project-URL: Homepage, https://github.com/yanghui1-arch/mwin.git
Requires-Python: >=3.12
License-File: LICENSE
Requires-Dist: click>=8.3.0
Requires-Dist: more-itertools>=10.8.0
Requires-Dist: openai>=1.108.2
Requires-Dist: requests>=2.32.5
Requires-Dist: uuid6>=2025.0.1
Dynamic: license-file
